LICENSE
MANIFEST.in
README.md
requirements.txt
setup.py
src/pii_extract_plg_regex/__init__.py
src/pii_extract_plg_regex/defs.py
src/pii_extract_plg_regex/plugin_loader.py
src/pii_extract_plg_regex.egg-info/PKG-INFO
src/pii_extract_plg_regex.egg-info/SOURCES.txt
src/pii_extract_plg_regex.egg-info/dependency_links.txt
src/pii_extract_plg_regex.egg-info/entry_points.txt
src/pii_extract_plg_regex.egg-info/requires.txt
src/pii_extract_plg_regex.egg-info/top_level.txt
src/pii_extract_plg_regex/modules/__init__.py
src/pii_extract_plg_regex/modules/any/__init__.py
src/pii_extract_plg_regex/modules/any/bitcoin_address.py
src/pii_extract_plg_regex/modules/any/credit_card.py
src/pii_extract_plg_regex/modules/any/email.py
src/pii_extract_plg_regex/modules/any/ip_address.py
src/pii_extract_plg_regex/modules/de/__init__.py
src/pii_extract_plg_regex/modules/de/any/__init__.py
src/pii_extract_plg_regex/modules/de/any/international_phone_number.py
src/pii_extract_plg_regex/modules/en/__init__.py
src/pii_extract_plg_regex/modules/en/any/__init__.py
src/pii_extract_plg_regex/modules/en/any/age.py
src/pii_extract_plg_regex/modules/en/any/international_phone_number.py
src/pii_extract_plg_regex/modules/en/au/__init__.py
src/pii_extract_plg_regex/modules/en/au/abn.py
src/pii_extract_plg_regex/modules/en/au/phone_number.py
src/pii_extract_plg_regex/modules/en/au/tfn.py
src/pii_extract_plg_regex/modules/en/ca/__init__.py
src/pii_extract_plg_regex/modules/en/ca/phone_number.py
src/pii_extract_plg_regex/modules/en/ca/social_insurance_number.py
src/pii_extract_plg_regex/modules/en/gb/__init__.py
src/pii_extract_plg_regex/modules/en/gb/phone_number.py
src/pii_extract_plg_regex/modules/en/gb/vat_number.py
src/pii_extract_plg_regex/modules/en/in_/__init__.py
src/pii_extract_plg_regex/modules/en/in_/aadhaar.py
src/pii_extract_plg_regex/modules/en/in_/phone_number.py
src/pii_extract_plg_regex/modules/en/us/__init__.py
src/pii_extract_plg_regex/modules/en/us/phone_number.py
src/pii_extract_plg_regex/modules/en/us/social_security_number.py
src/pii_extract_plg_regex/modules/en/us/zipcode.py
src/pii_extract_plg_regex/modules/es/__init__.py
src/pii_extract_plg_regex/modules/es/any/__init__.py
src/pii_extract_plg_regex/modules/es/any/international_phone_number.py
