Metadata-Version: 2.1
Name: pii-extract-plg-regex
Version: 0.5.1
Summary: Regex modules for the extraction of PII from text chunks
Home-page: https://github.com/piisa/pii-extract-plg-regex
Download-URL: https://github.com/piisa/pii-extract-plg-regex/tarball/v0.5.1
Author: Paulo Villegas
Author-email: paulo.vllgs@gmail.com
License: Apache
Keywords: PIISA, PII
Classifier: Programming Language :: Python :: 3 :: Only
Classifier: License :: OSI Approved :: Apache Software License
Classifier: Development Status :: 4 - Beta
Classifier: Topic :: Software Development :: Libraries :: Application Frameworks
Requires-Python: >=3.8
Provides-Extra: test
License-File: LICENSE
